Velox-0.5.1.dist-info/DESCRIPTION.rst
Velox-0.5.1.dist-info/METADATA
Velox-0.5.1.dist-info/RECORD
Velox-0.5.1.dist-info/WHEEL
Velox-0.5.1.dist-info/metadata.json
Velox-0.5.1.dist-info/top_level.txt
velox/__init__.py
velox/exceptions.py
velox/filesystem.py
velox/lite.py
velox/obj.py
velox/tools.py
velox/wrapper.py
